[{"AirlineCode":"AF","AirlineId":2,"AirlineName":"Air France (AF)","DestinationId":54,"DestinationName":"Paris Charles de Gaulle (CDG)","Direction":null,"FlightId":93,"FlightType":null,"OriginId":14,"OriginName":"Houston (IAH)","Route":null,"Type":null},{"AirlineCode":"NZ","AirlineId":25,"AirlineName":"Air New Zealand (NZ)","DestinationId":96,"DestinationName":"Auckland (AKL)","Direction":null,"FlightId":1369,"FlightType":null,"OriginId":14,"OriginName":"Houston (IAH)","Route":null,"Type":null},{"AirlineCode":"NH","AirlineId":21,"AirlineName":"All Nippon Airways (NH)","DestinationId":39,"DestinationName":"Tokyo Narita (NRT)","Direction":null,"FlightId":1309,"FlightType":null,"OriginId":14,"OriginName":"Houston (IAH)","Route":null,"Type":null},{"AirlineCode":"AV","AirlineId":26,"AirlineName":"Avianca (AV)","DestinationId":113,"DestinationName":"Salvador (SAL)","Direction":null,"FlightId":1052,"FlightType":null,"OriginId":14,"OriginName":"Houston (IAH)","Route":null,"Type":null},{"AirlineCode":"BA","AirlineId":4,"AirlineName":"British Airways (BA)","DestinationId":48,"DestinationName":"London Heathrow (LHR)","Direction":null,"FlightId":128,"FlightType":null,"OriginId":14,"OriginName":"Houston (IAH)","Route":null,"Type":null},{"AirlineCode":"KL","AirlineId":10,"AirlineName":"KLM (Royal Dutch Airlines) (KL)","DestinationId":43,"DestinationName":"Amsterdam (AMS)","Direction":null,"FlightId":404,"FlightType":null,"OriginId":14,"OriginName":"Houston (IAH)","Route":null,"Type":null},{"AirlineCode":"LH","AirlineId":11,"AirlineName":"Lufthansa (LH)","DestinationId":45,"DestinationName":"Frankfurt (FRA)","Direction":null,"FlightId":461,"FlightType":null,"OriginId":14,"OriginName":"Houston (IAH)","Route":null,"Type":null},{"AirlineCode":"TK","AirlineId":32,"AirlineName":"Turkish Airlines (TK)","DestinationId":142,"DestinationName":"Istanbul (IST)","Direction":null,"FlightId":1397,"FlightType":null,"OriginId":14,"OriginName":"Houston (IAH)","Route":null,"Type":null},{"AirlineCode":"UA","AirlineId":17,"AirlineName":"United Airlines (UA)","DestinationId":100,"DestinationName":"Panama City (PTY)","Direction":null,"FlightId":1470,"FlightType":null,"OriginId":14,"OriginName":"Houston (IAH)","Route":null,"Type":null},{"AirlineCode":"UA","AirlineId":17,"AirlineName":"United Airlines (UA)","DestinationId":43,"DestinationName":"Amsterdam (AMS)","Direction":null,"FlightId":640,"FlightType":null,"OriginId":14,"OriginName":"Houston (IAH)","Route":null,"Type":null},{"AirlineCode":"UA","AirlineId":17,"AirlineName":"United Airlines (UA)","DestinationId":54,"DestinationName":"Paris Charles de Gaulle (CDG)","Direction":null,"FlightId":641,"FlightType":null,"OriginId":14,"OriginName":"Houston (IAH)","Route":null,"Type":null},{"AirlineCode":"UA","AirlineId":17,"AirlineName":"United Airlines (UA)","DestinationId":48,"DestinationName":"London Heathrow (LHR)","Direction":null,"FlightId":642,"FlightType":null,"OriginId":14,"OriginName":"Houston (IAH)","Route":null,"Type":null},{"AirlineCode":"UA","AirlineId":17,"AirlineName":"United Airlines (UA)","DestinationId":39,"DestinationName":"Tokyo Narita (NRT)","Direction":null,"FlightId":643,"FlightType":null,"OriginId":14,"OriginName":"Houston (IAH)","Route":null,"Type":null},{"AirlineCode":"UA","AirlineId":17,"AirlineName":"United Airlines (UA)","DestinationId":110,"DestinationName":"Quito (UIO)","Direction":null,"FlightId":928,"FlightType":null,"OriginId":14,"OriginName":"Houston (IAH)","Route":null,"Type":null},{"AirlineCode":"UA","AirlineId":17,"AirlineName":"United Airlines (UA)","DestinationId":108,"DestinationName":"Caracas (CCS)","Direction":null,"FlightId":931,"FlightType":null,"OriginId":14,"OriginName":"Houston (IAH)","Route":null,"Type":null},{"AirlineCode":"UA","AirlineId":17,"AirlineName":"United Airlines (UA)","DestinationId":97,"DestinationName":"Lima (LIM)","Direction":null,"FlightId":932,"FlightType":null,"OriginId":14,"OriginName":"Houston (IAH)","Route":null,"Type":null},{"AirlineCode":"UA","AirlineId":17,"AirlineName":"United Airlines (UA)","DestinationId":99,"DestinationName":"Sao Paulo (GRU)","Direction":null,"FlightId":933,"FlightType":null,"OriginId":14,"OriginName":"Houston (IAH)","Route":null,"Type":null},{"AirlineCode":"UA","AirlineId":17,"AirlineName":"United Airlines (UA)","DestinationId":98,"DestinationName":"Buenos Aires (EZE)","Direction":null,"FlightId":934,"FlightType":null,"OriginId":14,"OriginName":"Houston (IAH)","Route":null,"Type":null},{"AirlineCode":"UA","AirlineId":17,"AirlineName":"United Airlines (UA)","DestinationId":107,"DestinationName":"Bogota (BOG)","Direction":null,"FlightId":937,"FlightType":null,"OriginId":14,"OriginName":"Houston (IAH)","Route":null,"Type":null},{"AirlineCode":"UA","AirlineId":17,"AirlineName":"United Airlines (UA)","DestinationId":104,"DestinationName":"Rio de Janeiro (GIG)","Direction":null,"FlightId":941,"FlightType":null,"OriginId":14,"OriginName":"Houston (IAH)","Route":null,"Type":null},{"AirlineCode":"UA","AirlineId":17,"AirlineName":"United Airlines (UA)","DestinationId":45,"DestinationName":"Frankfurt (FRA)","Direction":null,"FlightId":805,"FlightType":null,"OriginId":14,"OriginName":"Houston (IAH)","Route":null,"Type":null},{"AirlineCode":"UA","AirlineId":17,"AirlineName":"United Airlines (UA)","DestinationId":101,"DestinationName":"Santiago de Chile (SCL)","Direction":null,"FlightId":1176,"FlightType":null,"OriginId":14,"OriginName":"Houston (IAH)","Route":null,"Type":null},{"AirlineCode":"UA","AirlineId":17,"AirlineName":"United Airlines (UA)","DestinationId":52,"DestinationName":"Munich (MUC)","Direction":null,"FlightId":1138,"FlightType":null,"OriginId":14,"OriginName":"Houston (IAH)","Route":null,"Type":null}]