[{"AirportId":0,"AirportName":null,"Code":null,"InterviewerId":77,"InterviewerName":"DEL - Interviewer 1","IsActive":false},{"AirportId":0,"AirportName":null,"Code":null,"InterviewerId":78,"InterviewerName":"DEL - Interviewer 2","IsActive":false},{"AirportId":0,"AirportName":null,"Code":null,"InterviewerId":84,"InterviewerName":"DEL - Interviewer 3","IsActive":false},{"AirportId":0,"AirportName":null,"Code":null,"InterviewerId":85,"InterviewerName":"DEL - Interviewer 4","IsActive":false},{"AirportId":0,"AirportName":null,"Code":null,"InterviewerId":86,"InterviewerName":"DEL - Interviewer 5","IsActive":false},{"AirportId":0,"AirportName":null,"Code":null,"InterviewerId":87,"InterviewerName":"DEL - Interviewer 6","IsActive":false},{"AirportId":0,"AirportName":null,"Code":null,"InterviewerId":88,"InterviewerName":"DEL - Interviewer 7","IsActive":false}]